checkstyle/__init__.py
checkstyle/__main__.py
checkstyle/application.py
checkstyle/cli.py
checkstyle/utils/__init__.py
checkstyle/utils/parser.py
checkstyle/utils/store.py
checkstyle_cli-0.7.2.dist-info/licenses/LICENSE
checkstyle_cli-0.7.2.dist-info/METADATA
checkstyle_cli-0.7.2.dist-info/WHEEL
checkstyle_cli-0.7.2.dist-info/entry_points.txt
checkstyle_cli-0.7.2.dist-info/top_level.txt
checkstyle_cli-0.7.2.dist-info/RECORD
