Metadata-Version: 2.4
Name: checkstyle_cli
Version: 0.7.2
Summary: A command-line tool for checkstyle.
Home-page: https://github.com/junghoon-vans/checkstyle-cli
Author: junghoon-vans
Author-email: junghoon.ban@gmail.com
License: MIT
Classifier: Environment :: Console
Classifier: License :: OSI Approved :: MIT License
Classifier: Programming Language :: Python :: 3
Classifier: Programming Language :: Python :: 3 :: Only
Requires-Python: >=3.7
License-File: LICENSE
Requires-Dist: appdirs
Requires-Dist: requests
Requires-Dist: tqdm
Dynamic: license-file
